odoo/addons/account_payment_multi_deduction_budget_plan_detail/README.rst
odoo/addons/account_payment_multi_deduction_budget_plan_detail/__init__.py
odoo/addons/account_payment_multi_deduction_budget_plan_detail/__manifest__.py
odoo/addons/account_payment_multi_deduction_budget_plan_detail/hooks.py
odoo/addons/account_payment_multi_deduction_budget_plan_detail/models/__init__.py
odoo/addons/account_payment_multi_deduction_budget_plan_detail/models/account_analytic_dimension.py
odoo/addons/account_payment_multi_deduction_budget_plan_detail/readme/CONTRIBUTORS.md
odoo/addons/account_payment_multi_deduction_budget_plan_detail/readme/DESCRIPTION.md
odoo/addons/account_payment_multi_deduction_budget_plan_detail/static/description/icon.png
odoo/addons/account_payment_multi_deduction_budget_plan_detail/static/description/index.html
odoo/addons/account_payment_multi_deduction_budget_plan_detail/tests/__init__.py
odoo/addons/account_payment_multi_deduction_budget_plan_detail/tests/test_payment_multi_deduction_budget.py
odoo/addons/account_payment_multi_deduction_budget_plan_detail/wizard/__init__.py
odoo/addons/account_payment_multi_deduction_budget_plan_detail/wizard/account_payment_deduction.py
odoo/addons/account_payment_multi_deduction_budget_plan_detail/wizard/account_payment_register.py
odoo/addons/account_payment_multi_deduction_budget_plan_detail/wizard/account_payment_register_views.xml
odoo_addon_account_payment_multi_deduction_budget_plan_detail-18.0.1.0.3.dist-info/METADATA
odoo_addon_account_payment_multi_deduction_budget_plan_detail-18.0.1.0.3.dist-info/WHEEL
odoo_addon_account_payment_multi_deduction_budget_plan_detail-18.0.1.0.3.dist-info/top_level.txt
odoo_addon_account_payment_multi_deduction_budget_plan_detail-18.0.1.0.3.dist-info/RECORD
